pylibec/__init__.py
pylibec/ec.py
pylibec-0.0.1.dist-info/METADATA
pylibec-0.0.1.dist-info/WHEEL
pylibec-0.0.1.dist-info/top_level.txt
pylibec-0.0.1.dist-info/RECORD
